nltkaz/__init__.py
nltkaz/stem/__init__.py
nltkaz/stem/azwords.txt
nltkaz/stem/enwords.txt
nltkaz/stem/stemmer.py
nltkaz/stopwords/__init__.py
nltkaz/stopwords/stopwords.py
nltkaz/stopwords/stopwords.txt
nltkaz/tokenize/__init__.py
nltkaz/tokenize/tokenize.py
nltkaz-0.2.0.dist-info/METADATA
nltkaz-0.2.0.dist-info/WHEEL
nltkaz-0.2.0.dist-info/top_level.txt
nltkaz-0.2.0.dist-info/RECORD
