Metadata-Version: 2.4
Name: nltkaz
Version: 0.2.0
Summary: A natural language processing toolkit designed for the Azerbaijani language.
Author: Nagi Nagiyev
Author-email: nagiyevnagi01@gmail.com
Classifier: Programming Language :: Python :: 3
Classifier: Operating System :: OS Independent
Requires-Python: >=3.6
Requires-Dist: importlib_resources; python_version < "3.9"
Dynamic: author
Dynamic: author-email
Dynamic: classifier
Dynamic: description
Dynamic: description-content-type
Dynamic: requires-dist
Dynamic: requires-python
Dynamic: summary
